pyanom/__init__.py
pyanom/__version__.py
pyanom/density_ratio_estimation.py
pyanom/outlier_detection.py
pyanom/structure_learning.py
pyanom/subspace_methods.py
pyanom/utils.py
pyanom-0.0.2b1.dist-info/LICENSE
pyanom-0.0.2b1.dist-info/METADATA
pyanom-0.0.2b1.dist-info/WHEEL
pyanom-0.0.2b1.dist-info/top_level.txt
pyanom-0.0.2b1.dist-info/RECORD
